{
  "rooms" : {
    "intellect" : {
      "name" : "Mensa",
      "numberOfScouts" : 2
    },
    "physic" : {
      "name" : "Fysisk",
      "numberOfScouts" : 1
    },
    "mental" : {
      "name" : "Psykisk",
      "numberOfScouts" : 1
    },
    "precision" : {
      "name" : "Præcision",
      "numberOfScouts" : 2
    },
    "attention" : {
      "name" : "Opmærksomhed",
      "numberOfScouts" : 1
    },
    "creative" : {
      "name" : "Kreativ",
      "numberOfScouts" : 4
    }
  },
  "scouts" : {
    "123456" : {
      "arrived" : true,
      "name" : "Rasmus Jensen"
    },
    "234567" : {
      "arrived" : false,
      "name" : "Morten Fjord"
    }
  }
}
